Metadata-Version: 1.1
Name: BabelEnte
Version: 0.4.3
Summary: Entity extractioN, Translation and Evaluation using BabelFy
Home-page: https://github.com/proycon/babelente
Author: Maarten van Gompel, Iris Hendrickx
Author-email: proycon@anaproy.nl
License: GPL
Keywords: nlp computational_linguistics entities wikipedia dbpedia linguistics tramooc
Platform: UNKNOWN
Classifier: Development Status :: 4 - Beta
Classifier: Topic :: Text Processing :: Linguistic
Classifier: Programming Language :: Python :: 3
Classifier: Operating System :: POSIX
Classifier: Intended Audience :: Science/Research
Classifier: License :: OSI Approved :: GNU General Public License v3 (GPLv3)
